{
    "random_1": {
        "training": {
            "loss": [
                3.876308196940238
            ],
            "accuracy": [
                0.13356705414958706
            ]
        },
        "validation": {
            "random_1": {
                "accuracy": [
                    0.36113278208107785
                ]
            }
        }
    },
    "random_2": {
        "training": {
            "loss": [
                3.8645773717404377
            ],
            "accuracy": [
                0.13025628024255045
            ]
        },
        "validation": {
            "random_2": {
                "accuracy": [
                    0.37899340770791073
                ]
            }
        }
    },
    "random_3": {
        "training": {
            "loss": [
                3.8502274628343254
            ],
            "accuracy": [
                0.13383523173796477
            ]
        },
        "validation": {
            "random_3": {
                "accuracy": [
                    0.37752086915544275
                ]
            }
        }
    },
    "random_4": {
        "training": {
            "loss": [
                3.853315402237929
            ],
            "accuracy": [
                0.1335524262871752
            ]
        },
        "validation": {
            "random_4": {
                "accuracy": [
                    0.3679688719174925
                ]
            }
        }
    },
    "random_5": {
        "training": {
            "loss": [
                3.9098834594896794
            ],
            "accuracy": [
                0.1211284911958973
            ]
        },
        "validation": {
            "random_5": {
                "accuracy": [
                    0.3495670152000675
                ]
            }
        }
    },
    "random_6": {
        "training": {
            "loss": [
                3.876201028997951
            ],
            "accuracy": [
                0.1300514901083333
            ]
        },
        "validation": {
            "random_6": {
                "accuracy": [
                    0.35364331410816185
                ]
            }
        }
    },
    "random_7": {
        "training": {
            "loss": [
                3.8371532804825725
            ],
            "accuracy": [
                0.13351829461828932
            ]
        },
        "validation": {
            "random_7": {
                "accuracy": [
                    0.38761409736308317
                ]
            }
        }
    },
    "random_8": {
        "training": {
            "loss": [
                3.867154702211732
            ],
            "accuracy": [
                0.13437646279833138
            ]
        },
        "validation": {
            "random_8": {
                "accuracy": [
                    0.33352999694448937
                ]
            }
        }
    },
    "random_9": {
        "training": {
            "loss": [
                3.8962779688303177
            ],
            "accuracy": [
                0.13451786550861344
            ]
        },
        "validation": {
            "random_9": {
                "accuracy": [
                    0.37094808084244174
                ]
            }
        }
    },
    "random_10": {
        "training": {
            "loss": [
                3.846393708525033
            ],
            "accuracy": [
                0.13754583399508594
            ]
        },
        "validation": {
            "random_10": {
                "accuracy": [
                    0.3696315728022167
                ]
            }
        }
    },
    "cont_1": {
        "training": {
            "loss": [
                3.8103423007361545
            ],
            "accuracy": [
                0.14603974880238818
            ]
        },
        "validation": {
            "cont_1": {
                "accuracy": [
                    0.3976195584567033
                ]
            },
            "cont_2": {
                "accuracy": [
                    0.2329439070173983
                ]
            },
            "cont_3": {
                "accuracy": [
                    0.23896571229123198
                ]
            },
            "cont_4": {
                "accuracy": [
                    0.23937041661560415
                ]
            },
            "cont_5": {
                "accuracy": [
                    0.2376004447197092
                ]
            },
            "cont_6": {
                "accuracy": [
                    0.2301987439817154
                ]
            },
            "cont_7": {
                "accuracy": [
                    0.24083320334039884
                ]
            },
            "cont_8": {
                "accuracy": [
                    0.23839034953175403
                ]
            },
            "cont_9": {
                "accuracy": [
                    0.23530386956540855
                ]
            },
            "cont_10": {
                "accuracy": [
                    0.23349489002634014
                ]
            }
        }
    },
    "cont_2": {
        "training": {
            "loss": [
                3.0143486853787187
            ],
            "accuracy": [
                0.26864565455526657
            ]
        },
        "validation": {
            "cont_1": {
                "accuracy": [
                    0.36149847870182555
                ]
            },
            "cont_2": {
                "accuracy": [
                    0.5046857935178111
                ]
            },
            "cont_3": {
                "accuracy": [
                    0.31035457950455664
                ]
            },
            "cont_4": {
                "accuracy": [
                    0.317083398360026
                ]
            },
            "cont_5": {
                "accuracy": [
                    0.3097499610202549
                ]
            },
            "cont_6": {
                "accuracy": [
                    0.31218793885461216
                ]
            },
            "cont_7": {
                "accuracy": [
                    0.3169273677873321
                ]
            },
            "cont_8": {
                "accuracy": [
                    0.31397253867336994
                ]
            },
            "cont_9": {
                "accuracy": [
                    0.31289982838031005
                ]
            },
            "cont_10": {
                "accuracy": [
                    0.31068614451686943
                ]
            }
        }
    },
    "cont_3": {
        "training": {
            "loss": [
                2.7381066187883727
            ],
            "accuracy": [
                0.31489409430757254
            ]
        },
        "validation": {
            "cont_1": {
                "accuracy": [
                    0.3806609845669226
                ]
            },
            "cont_2": {
                "accuracy": [
                    0.4338430332484642
                ]
            },
            "cont_3": {
                "accuracy": [
                    0.5627828054205641
                ]
            },
            "cont_4": {
                "accuracy": [
                    0.35392611952872594
                ]
            },
            "cont_5": {
                "accuracy": [
                    0.35190259793709067
                ]
            },
            "cont_6": {
                "accuracy": [
                    0.3491135512839466
                ]
            },
            "cont_7": {
                "accuracy": [
                    0.3506884849337487
                ]
            },
            "cont_8": {
                "accuracy": [
                    0.3528339054594175
                ]
            },
            "cont_9": {
                "accuracy": [
                    0.34943048840362206
                ]
            },
            "cont_10": {
                "accuracy": [
                    0.3445789124854438
                ]
            }
        }
    },
    "cont_4": {
        "training": {
            "loss": [
                2.6072150768663045
            ],
            "accuracy": [
                0.3465585504898435
            ]
        },
        "validation": {
            "cont_1": {
                "accuracy": [
                    0.39405035887963874
                ]
            },
            "cont_2": {
                "accuracy": [
                    0.4207364643563122
                ]
            },
            "cont_3": {
                "accuracy": [
                    0.4675163832204095
                ]
            },
            "cont_4": {
                "accuracy": [
                    0.5868212670148265
                ]
            },
            "cont_5": {
                "accuracy": [
                    0.36879290842864865
                ]
            },
            "cont_6": {
                "accuracy": [
                    0.36728623811661837
                ]
            },
            "cont_7": {
                "accuracy": [
                    0.3735469652237805
                ]
            },
            "cont_8": {
                "accuracy": [
                    0.374663559104076
                ]
            },
            "cont_9": {
                "accuracy": [
                    0.36879290842864865
                ]
            },
            "cont_10": {
                "accuracy": [
                    0.3699338820594803
                ]
            }
        }
    },
    "cont_5": {
        "training": {
            "loss": [
                2.5294098242301244
            ],
            "accuracy": [
                0.36440454831471547
            ]
        },
        "validation": {
            "cont_1": {
                "accuracy": [
                    0.40880500079410315
                ]
            },
            "cont_2": {
                "accuracy": [
                    0.4246177251392156
                ]
            },
            "cont_3": {
                "accuracy": [
                    0.46060227803719694
                ]
            },
            "cont_4": {
                "accuracy": [
                    0.49413910127314786
                ]
            },
            "cont_5": {
                "accuracy": [
                    0.6005129505848062
                ]
            },
            "cont_6": {
                "accuracy": [
                    0.38798467001856946
                ]
            },
            "cont_7": {
                "accuracy": [
                    0.39658585583704237
                ]
            },
            "cont_8": {
                "accuracy": [
                    0.394898775262233
                ]
            },
            "cont_9": {
                "accuracy": [
                    0.3830843345388679
                ]
            },
            "cont_10": {
                "accuracy": [
                    0.38961811517846995
                ]
            }
        }
    },
    "cont_6": {
        "training": {
            "loss": [
                2.4398769986556945
            ],
            "accuracy": [
                0.38024652838465167
            ]
        },
        "validation": {
            "cont_1": {
                "accuracy": [
                    0.42110216103751086
                ]
            },
            "cont_2": {
                "accuracy": [
                    0.43472558126971883
                ]
            },
            "cont_3": {
                "accuracy": [
                    0.45656011082821396
                ]
            },
            "cont_4": {
                "accuracy": [
                    0.4778436573475418
                ]
            },
            "cont_5": {
                "accuracy": [
                    0.5135502809201486
                ]
            },
            "cont_6": {
                "accuracy": [
                    0.6254242081912971
                ]
            },
            "cont_7": {
                "accuracy": [
                    0.41468052738336714
                ]
            },
            "cont_8": {
                "accuracy": [
                    0.4090487986017192
                ]
            },
            "cont_9": {
                "accuracy": [
                    0.3986142534029653
                ]
            },
            "cont_10": {
                "accuracy": [
                    0.4019640349834009
                ]
            }
        }
    },
    "cont_7": {
        "training": {
            "loss": [
                2.3602190960735143
            ],
            "accuracy": [
                0.3990725932933738
            ]
        },
        "validation": {
            "cont_1": {
                "accuracy": [
                    0.42426665632042876
                ]
            },
            "cont_2": {
                "accuracy": [
                    0.43327254643304836
                ]
            },
            "cont_3": {
                "accuracy": [
                    0.45466336408444885
                ]
            },
            "cont_4": {
                "accuracy": [
                    0.47197788276730396
                ]
            },
            "cont_5": {
                "accuracy": [
                    0.4892728975530087
                ]
            },
            "cont_6": {
                "accuracy": [
                    0.5218979169824303
                ]
            },
            "cont_7": {
                "accuracy": [
                    0.6346105086875977
                ]
            },
            "cont_8": {
                "accuracy": [
                    0.41058472469902424
                ]
            },
            "cont_9": {
                "accuracy": [
                    0.4084051724137931
                ]
            },
            "cont_10": {
                "accuracy": [
                    0.40753725231540133
                ]
            }
        }
    },
    "cont_8": {
        "training": {
            "loss": [
                2.348889178243177
            ],
            "accuracy": [
                0.40120826181001645
            ]
        },
        "validation": {
            "cont_1": {
                "accuracy": [
                    0.43550573413318844
                ]
            },
            "cont_2": {
                "accuracy": [
                    0.44269776876267747
                ]
            },
            "cont_3": {
                "accuracy": [
                    0.4591004837599052
                ]
            },
            "cont_4": {
                "accuracy": [
                    0.46663871123389344
                ]
            },
            "cont_5": {
                "accuracy": [
                    0.4874834217599633
                ]
            },
            "cont_6": {
                "accuracy": [
                    0.5015895615726649
                ]
            },
            "cont_7": {
                "accuracy": [
                    0.5383932751284168
                ]
            },
            "cont_8": {
                "accuracy": [
                    0.6437041660351396
                ]
            },
            "cont_9": {
                "accuracy": [
                    0.42249668436408283
                ]
            },
            "cont_10": {
                "accuracy": [
                    0.41531927759700565
                ]
            }
        }
    },
    "cont_9": {
        "training": {
            "loss": [
                2.3219580444796333
            ],
            "accuracy": [
                0.4118427212291509
            ]
        },
        "validation": {
            "cont_1": {
                "accuracy": [
                    0.44364858012170383
                ]
            },
            "cont_2": {
                "accuracy": [
                    0.4442824543610548
                ]
            },
            "cont_3": {
                "accuracy": [
                    0.457101341918806
                ]
            },
            "cont_4": {
                "accuracy": [
                    0.468969417996629
                ]
            },
            "cont_5": {
                "accuracy": [
                    0.47412330323252183
                ]
            },
            "cont_6": {
                "accuracy": [
                    0.4893070291916691
                ]
            },
            "cont_7": {
                "accuracy": [
                    0.5095958808856368
                ]
            },
            "cont_8": {
                "accuracy": [
                    0.5407239818911523
                ]
            },
            "cont_9": {
                "accuracy": [
                    0.6488775550472808
                ]
            },
            "cont_10": {
                "accuracy": [
                    0.4257782025462957
                ]
            }
        }
    },
    "cont_10": {
        "training": {
            "loss": [
                2.284186711417734
            ],
            "accuracy": [
                0.41449036511156184
            ]
        },
        "validation": {
            "cont_1": {
                "accuracy": [
                    0.44906576688101035
                ]
            },
            "cont_2": {
                "accuracy": [
                    0.4459939148073022
                ]
            },
            "cont_3": {
                "accuracy": [
                    0.4631865346165748
                ]
            },
            "cont_4": {
                "accuracy": [
                    0.47397702448750123
                ]
            },
            "cont_5": {
                "accuracy": [
                    0.47823373383972756
                ]
            },
            "cont_6": {
                "accuracy": [
                    0.4817444219066937
                ]
            },
            "cont_7": {
                "accuracy": [
                    0.5003120612662898
                ]
            },
            "cont_8": {
                "accuracy": [
                    0.5176314558025306
                ]
            },
            "cont_9": {
                "accuracy": [
                    0.542123381192012
                ]
            },
            "cont_10": {
                "accuracy": [
                    0.6469808083035158
                ]
            }
        }
    },
    "training_metrics": {
        "training": {},
        "validation": {
            "cont_1": {
                "accuracy": [
                    0.44906576688101035
                ],
                "flatness": [
                    0.6338777053915471
                ]
            },
            "cont_2": {
                "accuracy": [
                    0.4459939148073022
                ],
                "flatness": [
                    0.6245102648339264
                ]
            },
            "cont_3": {
                "accuracy": [
                    0.4631865346165748
                ],
                "flatness": [
                    0.5546421553318557
                ]
            },
            "cont_4": {
                "accuracy": [
                    0.47397702448750123
                ],
                "flatness": [
                    0.5442422734561728
                ]
            },
            "cont_5": {
                "accuracy": [
                    0.47823373383972756
                ],
                "flatness": [
                    0.5725640521191814
                ]
            },
            "cont_6": {
                "accuracy": [
                    0.4817444219066937
                ],
                "flatness": [
                    0.577876725283673
                ]
            },
            "cont_7": {
                "accuracy": [
                    0.5003120612662898
                ],
                "flatness": [
                    0.6087311885514526
                ]
            },
            "cont_8": {
                "accuracy": [
                    0.5176314558025306
                ],
                "flatness": [
                    0.5580707990996123
                ]
            },
            "cont_9": {
                "accuracy": [
                    0.542123381192012
                ],
                "flatness": [
                    0.514335561121497
                ]
            },
            "cont_10": {
                "accuracy": [
                    0.6469808083035158
                ],
                "flatness": [
                    0.5289097298027239
                ]
            }
        }
    }
}